lzhbaidutranslate/__init__.py
lzhbaidutranslate/trans.py
lzhbaidutranslate-1.1.dist-info/METADATA
lzhbaidutranslate-1.1.dist-info/WHEEL
lzhbaidutranslate-1.1.dist-info/top_level.txt
lzhbaidutranslate-1.1.dist-info/RECORD
