Metadata-Version: 2.4
Name: lzhbaidutranslate
Version: 1.1
Summary: 封装百度翻译 API, 翻译字符串或字符串列表
Author-email: lzh <zhhtdm@hotmail.com>
License: MIT
Project-URL: Homepage, https://github.com/zhhtdm/baidu-translate
Project-URL: Repository, https://github.com/zhhtdm/baidu-translate
Requires-Python: >=3.10
Requires-Dist: requests
Requires-Dist: aiohttp
